nat/__init__.py
nat/ageResolver.py
nat/aggregators.py
nat/annotTextLocalizer.py
nat/annotation.py
nat/annotationSearch.py
nat/condition.py
nat/equivalenceFinder.py
nat/gitManager.py
nat/id.py
nat/modelingParameter.py
nat/ontoDic.py
nat/ontoManager.py
nat/ontoServ.py
nat/paramDesc.py
nat/paramSample.py
nat/parameterInstance.py
nat/plot.py
nat/relationship.py
nat/restClient.py
nat/restServer.py
nat/runOCR.py
nat/scigraph_client.py
nat/scrapingText.py
nat/tag.py
nat/tagUtilities.py
nat/treeData.py
nat/utils.py
nat/values.py
nat/variable.py
nat/zotero_wrap.py
nat/data/additionsToOntologies.csv
nat/data/modelingDictionary.csv
nat/data/modelingDictionary_relationships.csv
nat-0.4.3.data/data/LICENSE.txt
nat-0.4.3.dist-info/METADATA
nat-0.4.3.dist-info/RECORD
nat-0.4.3.dist-info/WHEEL
nat-0.4.3.dist-info/top_level.txt
