Metadata-Version: 2.1
Name: nat
Version: 0.4.3
Summary: Module to use the annotations created with NeuroCurator.
Home-page: https://github.com/BlueBrain/nat
Author: Christian O'Reilly, Pierre-Alexandre Fonta
Author-email: christian.oreilly@epfl.ch, pierre-alexandre.fonta@epfl.ch
License: GPLv3
Keywords: neuroscience annotation curation literature modeling parameters
Platform: UNKNOWN
Classifier: Development Status :: 3 - Alpha
Classifier: Intended Audience :: Science/Research
Classifier: Intended Audience :: Developers
Classifier: Topic :: Scientific/Engineering
Classifier: Topic :: Software Development :: Libraries :: Python Modules
Classifier: License :: OSI Approved :: GNU General Public License v3 (GPLv3)
Classifier: License :: Free for non-commercial use
Classifier: Programming Language :: Python :: 3 :: Only
Classifier: Operating System :: MacOS
Classifier: Operating System :: POSIX :: Linux
Classifier: Operating System :: Microsoft :: Windows
Classifier: Natural Language :: English
Requires-Python: >=3
Provides-Extra: test
Requires-Dist: beautifulsoup4
Requires-Dist: gitpython
Requires-Dist: lxml
Requires-Dist: numpy
Requires-Dist: pandas
Requires-Dist: parse
Requires-Dist: pyzotero
Requires-Dist: quantities
Requires-Dist: scipy
Requires-Dist: wand
Provides-Extra: test
Requires-Dist: pytest; extra == 'test'
Requires-Dist: pytest-cov; extra == 'test'
Requires-Dist: pytest-lazy-fixture; extra == 'test'
Requires-Dist: pytest-mock; extra == 'test'
